vocalizr/__init__.py
vocalizr/__main__.py
vocalizr/app/__init__.py
vocalizr/app/builder.py
vocalizr/app/choices.py
vocalizr/app/logger.py
vocalizr/app/runner.py
vocalizr/app/settings.py
vocalizr-0.1.0.dist-info/WHEEL
vocalizr-0.1.0.dist-info/entry_points.txt
vocalizr-0.1.0.dist-info/METADATA
vocalizr-0.1.0.dist-info/RECORD
