Metadata-Version: 2.3
Name: vocalizr
Version: 0.1.0
Summary: Voice Generator part of the Chatacter Backend
Keywords: audio,kokoro,voice
Author: Mohamed Hisham Abdelzaher
Author-email: Mohamed Hisham Abdelzaher <mohamed.hisham.abdelzaher@gmail.com>
Classifier: Environment :: GPU :: NVIDIA CUDA :: 12 :: 12.4
Classifier: Programming Language :: Python :: 3.12
Classifier: Programming Language :: Python :: 3.13
Classifier: Topic :: Scientific/Engineering :: Artificial Intelligence
Requires-Dist: gradio[mcp]>=5.49.1
Requires-Dist: kokoro>=0.9.4
Requires-Dist: pip>=25.3
Requires-Dist: pyfiglet>=1.0.4
Requires-Dist: soundfile>=0.13.1
Requires-Python: >=3.12, <3.13
Project-URL: Issues, https://github.com/AlphaSphereDotAI/vocalizr/issues
Project-URL: Repository, https://github.com/AlphaSphereDotAI/vocalizr.git
Project-URL: Twitter, https://x.com/AlphaSphereAI
